wsgi_harakiri/__init__.py
wsgi_harakiri-1.0.0.dist-info/DESCRIPTION.rst
wsgi_harakiri-1.0.0.dist-info/METADATA
wsgi_harakiri-1.0.0.dist-info/RECORD
wsgi_harakiri-1.0.0.dist-info/WHEEL
wsgi_harakiri-1.0.0.dist-info/metadata.json
wsgi_harakiri-1.0.0.dist-info/top_level.txt
