Metadata-Version: 2.0
Name: wsgi-harakiri
Version: 1.0.0
Summary: WSGI Middleware that implements a customizable 'harakiri' like  uWSGI
Home-page: https://github.com/adamchainz/wsgi-harakiri
Author: Adam Johnson
Author-email: me@adamj.eu
License: ISCL
Keywords: WSGI,Harakiri
Platform: UNKNOWN
Classifier: Development Status :: 5 - Production/Stable
Classifier: Intended Audience :: Developers
Classifier: License :: OSI Approved :: ISC License (ISCL)
Classifier: Natural Language :: English
Classifier: Operating System :: OS Independent
Classifier: Programming Language :: Python :: 2
Classifier: Programming Language :: Python :: 2.7
Classifier: Programming Language :: Python :: 3
Classifier: Programming Language :: Python :: 3.4
Classifier: Programming Language :: Python :: 3.5
Classifier: Programming Language :: Python
Classifier: Topic :: Software Development
Requires-Dist: six
